LICENSE
MANIFEST.in
README
README.rst
setup.py
asap/TODO-clingo.py
asap/TODO-common.py
asap/TODO-dlvhex.py
asap/__init__.py
asap.egg-info/PKG-INFO
asap.egg-info/SOURCES.txt
asap.egg-info/dependency_links.txt
asap.egg-info/not-zip-safe
asap.egg-info/top_level.txt
asap/clingo/__init__.py
asap/clingo/buildclingo.py
asap/clingo/common.py
asap/clingo/engine.py
asap/core/ASAP-Rewriter.jar
asap/core/__init__.py
asap/core/api.py
asap/examples/__init__.py
asap/examples/minimal-helloworld1.asap
asap/examples/minimal-helloworld2.asap
asap/examples/minimal-onoffswitch.asap
asap/plugins/__init__.py
asap/plugins/solver.py
asap/plugins/stdlib.py
asap/plugins/timer.py
asap/plugins/tkinter.py
asap_aplagent/__init__.py
asap_tetris/__init__.py
bin/asap
bin/asap-aplagent
bin/asap-example-onoffswitch
bin/asap-tetris