Metadata-Version: 1.1
Name: asap
Version: 2.0.0a8
Summary: ASAP Answer Set Application Programming
Home-page: https://bitbucket.org/peterschueller/asap-aspetris
Author: Peter Schuller, Antonius Weinzierl
Author-email: schueller.p@gmail.com
License: BSD
Platform: UNKNOWN
Classifier: Development Status :: 4 - Beta
Classifier: Programming Language :: Python :: 3
Classifier: Intended Audience :: Developers
Classifier: Intended Audience :: Information Technology
Classifier: Intended Audience :: Science/Research
Classifier: License :: OSI Approved :: BSD License
Classifier: Natural Language :: English
Classifier: Topic :: Scientific/Engineering :: Artificial Intelligence
Classifier: Topic :: Scientific/Engineering :: Information Analysis
Classifier: Topic :: Scientific/Engineering :: Mathematics
Classifier: Topic :: Utilities
